Metadata-Version: 2.1
Name: jesseapp123
Version: 3.0.0
Summary: Track time beautifully.
Home-page: https://github.com/codemouse92/timecard
Author: Jason C. McDonald
Author-email: "Jason C. McDonald" <codemouse92@outlook.com>
Maintainer-email: "Jason C. McDonald" <codemouse92@outlook.com>
License: BSD 3-Clause License
Project-URL: Homepage, https://codemouse92.github.io/Timecard/
Project-URL: Repository, https://github.com/codemouse92/timecard
Project-URL: Issues, https://github.com/codemouse92/timecard/issues
Project-URL: Funding, https://github.com/sponsors/CodeMouse92
Keywords: time,tracking,office,clock,tool,utility
Classifier: Development Status :: 5 - Production/Stable
Classifier: Environment :: X11 Applications :: Qt
Classifier: Natural Language :: English
Classifier: Operating System :: OS Independent
Classifier: Intended Audience :: End Users/Desktop
Classifier: Topic :: Office/Business
Classifier: License :: OSI Approved :: BSD License
Classifier: Programming Language :: Python
Classifier: Programming Language :: Python :: 3
Classifier: Programming Language :: Python :: 3.6
Classifier: Programming Language :: Python :: 3.7
Classifier: Programming Language :: Python :: 3.8
Classifier: Programming Language :: Python :: 3.9
Classifier: Programming Language :: Python :: 3.10
Classifier: Programming Language :: Python :: 3 :: Only
Classifier: Programming Language :: Python :: Implementation :: CPython
Requires-Python: <4,>=3.6
License-File: LICENSE
Requires-Dist: appdirs (>=1.4.4)
Requires-Dist: PySide6 (>=6.5.0)
Provides-Extra: test
Requires-Dist: pytest ; extra == 'test'
